routingfilter/__init__.py
routingfilter/dictquery.py
routingfilter/routing.py
routingfilter/filters/__init__.py
routingfilter/filters/filters.py
routingfilter/filters/results.py
routingfilter/filters/rule.py
routingfilter/filters/stream.py
routingfilter-2.3.3.dist-info/LICENSE.txt
routingfilter-2.3.3.dist-info/METADATA
routingfilter-2.3.3.dist-info/WHEEL
routingfilter-2.3.3.dist-info/top_level.txt
routingfilter-2.3.3.dist-info/RECORD
