Metadata-Version: 2.1
Name: routingfilter
Version: 2.3.3
Summary: Generic Business Logic Implementation for Routing objects as python dictionaries
Home-page: https://github.com/certego/RoutingFilter
Author: Certego S.r.l.
Author-email: support@certego.net
License: GNU LGPLv3
Classifier: License :: OSI Approved :: GNU Lesser General Public License v3 (LGPLv3)
Classifier: Operating System :: OS Independent
Classifier: Programming Language :: Python :: 3
Classifier: Topic :: Software Development :: Libraries :: Python Modules
Requires-Python: >=3.8
License-File: LICENSE.txt
Requires-Dist: IPy ~=1.1
Requires-Dist: macaddress ~=2.0.2
